{
    "1570838400": {
        "time": 1570838400,
        "low": 8261.46,
        "high": 8313.92,
        "open": 8263.02,
        "close": 8281.57,
        "volume": 210.10939337
    },
    "1570842000": {
        "time": 1570842000,
        "low": 8270.53,
        "high": 8332.0,
        "open": 8281.57,
        "close": 8315.96,
        "volume": 103.49991692
    },
    "1570845600": {
        "time": 1570845600,
        "low": 8307.15,
        "high": 8334.73,
        "open": 8316.43,
        "close": 8309.92,
        "volume": 93.98990514
    },
    "1570849200": {
        "time": 1570849200,
        "low": 8305.25,
        "high": 8327.25,
        "open": 8309.92,
        "close": 8317.39,
        "volume": 87.42600231
    },
    "1570852800": {
        "time": 1570852800,
        "low": 8315.31,
        "high": 8336.89,
        "open": 8317.39,
        "close": 8325.08,
        "volume": 66.94392756
    },
    "1570856400": {
        "time": 1570856400,
        "low": 8320.3,
        "high": 8363.11,
        "open": 8325.48,
        "close": 8344.26,
        "volume": 123.01253937
    },
    "1570860000": {
        "time": 1570860000,
        "low": 8343.51,
        "high": 8364.0,
        "open": 8344.28,
        "close": 8352.12,
        "volume": 85.94591443
    },
    "1570863600": {
        "time": 1570863600,
        "low": 8336.37,
        "high": 8357.01,
        "open": 8352.12,
        "close": 8348.24,
        "volume": 51.4780781
    },
    "1570867200": {
        "time": 1570867200,
        "low": 8338.71,
        "high": 8356.04,
        "open": 8348.24,
        "close": 8355.44,
        "volume": 29.02507465
    },
    "1570870800": {
        "time": 1570870800,
        "low": 8350.63,
        "high": 8375.05,
        "open": 8355.44,
        "close": 8350.64,
        "volume": 60.49600987
    },
    "1570874400": {
        "time": 1570874400,
        "low": 8301.5,
        "high": 8350.63,
        "open": 8350.63,
        "close": 8322.08,
        "volume": 65.70865266
    },
    "1570878000": {
        "time": 1570878000,
        "low": 8312.01,
        "high": 8348.0,
        "open": 8322.08,
        "close": 8327.5,
        "volume": 130.46659543
    },
    "1570881600": {
        "time": 1570881600,
        "low": 8319.01,
        "high": 8349.85,
        "open": 8327.5,
        "close": 8347.86,
        "volume": 66.15900839
    },
    "1570885200": {
        "time": 1570885200,
        "low": 8325.91,
        "high": 8350.0,
        "open": 8347.86,
        "close": 8339.88,
        "volume": 117.32382733
    },
    "1570888800": {
        "time": 1570888800,
        "low": 8317.65,
        "high": 8425.0,
        "open": 8339.88,
        "close": 8396.05,
        "volume": 445.50748764
    },
    "1570892400": {
        "time": 1570892400,
        "low": 8366.09,
        "high": 8405.0,
        "open": 8397.85,
        "close": 8387.63,
        "volume": 175.43362074
    },
    "1570896000": {
        "time": 1570896000,
        "low": 8336.31,
        "high": 8407.0,
        "open": 8386.5,
        "close": 8342.96,
        "volume": 174.52171799
    },
    "1570899600": {
        "time": 1570899600,
        "low": 8330.84,
        "high": 8355.77,
        "open": 8342.96,
        "close": 8332.09,
        "volume": 120.56153641
    },
    "1570903200": {
        "time": 1570903200,
        "low": 8292.56,
        "high": 8339.65,
        "open": 8332.08,
        "close": 8318.01,
        "volume": 185.32604278
    },
    "1570906800": {
        "time": 1570906800,
        "low": 8296.45,
        "high": 8332.98,
        "open": 8318.0,
        "close": 8316.0,
        "volume": 178.42258987
    },
    "1570910400": {
        "time": 1570910400,
        "low": 8315.99,
        "high": 8349.99,
        "open": 8316.0,
        "close": 8346.35,
        "volume": 94.60281028
    },
    "1570914000": {
        "time": 1570914000,
        "low": 8323.65,
        "high": 8346.91,
        "open": 8346.46,
        "close": 8340.0,
        "volume": 155.58079189
    },
    "1570917600": {
        "time": 1570917600,
        "low": 8332.53,
        "high": 8350.0,
        "open": 8340.0,
        "close": 8334.49,
        "volume": 113.99502935
    },
    "1570921200": {
        "time": 1570921200,
        "low": 8305.51,
        "high": 8342.83,
        "open": 8332.56,
        "close": 8309.03,
        "volume": 110.86803703
    }
}