{
    "1519603200": {
        "time": 1519603200,
        "low": 9547.0,
        "high": 9628.0,
        "open": 9600.0,
        "close": 9593.0,
        "volume": 337.47083506
    },
    "1519606800": {
        "time": 1519606800,
        "low": 9592.99,
        "high": 9733.0,
        "open": 9593.0,
        "close": 9726.34,
        "volume": 792.27425547
    },
    "1519610400": {
        "time": 1519610400,
        "low": 9675.88,
        "high": 9779.49,
        "open": 9726.34,
        "close": 9740.0,
        "volume": 715.09252609
    },
    "1519614000": {
        "time": 1519614000,
        "low": 9590.0,
        "high": 9740.0,
        "open": 9740.0,
        "close": 9633.03,
        "volume": 532.05525649
    },
    "1519617600": {
        "time": 1519617600,
        "low": 9575.01,
        "high": 9679.56,
        "open": 9633.03,
        "close": 9675.79,
        "volume": 480.98912298
    },
    "1519621200": {
        "time": 1519621200,
        "low": 9578.9,
        "high": 9685.0,
        "open": 9675.83,
        "close": 9624.71,
        "volume": 282.78489416
    },
    "1519624800": {
        "time": 1519624800,
        "low": 9430.0,
        "high": 9643.06,
        "open": 9624.71,
        "close": 9430.74,
        "volume": 447.08245808
    },
    "1519628400": {
        "time": 1519628400,
        "low": 9428.0,
        "high": 9499.96,
        "open": 9430.75,
        "close": 9497.94,
        "volume": 258.99190898
    },
    "1519632000": {
        "time": 1519632000,
        "low": 9404.0,
        "high": 9497.94,
        "open": 9497.94,
        "close": 9457.01,
        "volume": 304.28504024
    },
    "1519635600": {
        "time": 1519635600,
        "low": 9454.79,
        "high": 9530.0,
        "open": 9457.01,
        "close": 9488.61,
        "volume": 219.29893767
    },
    "1519639200": {
        "time": 1519639200,
        "low": 9483.18,
        "high": 9722.66,
        "open": 9488.54,
        "close": 9699.82,
        "volume": 437.15178155
    },
    "1519642800": {
        "time": 1519642800,
        "low": 9672.08,
        "high": 9759.0,
        "open": 9699.83,
        "close": 9744.0,
        "volume": 386.40107318
    },
    "1519646400": {
        "time": 1519646400,
        "low": 9654.19,
        "high": 9912.0,
        "open": 9744.0,
        "close": 9896.03,
        "volume": 731.95731455
    },
    "1519650000": {
        "time": 1519650000,
        "low": 9896.03,
        "high": 10227.13,
        "open": 9896.04,
        "close": 10124.98,
        "volume": 2583.91222176
    },
    "1519653600": {
        "time": 1519653600,
        "low": 10117.82,
        "high": 10350.0,
        "open": 10124.99,
        "close": 10200.0,
        "volume": 1807.27091641
    },
    "1519657200": {
        "time": 1519657200,
        "low": 10144.0,
        "high": 10247.95,
        "open": 10200.0,
        "close": 10221.0,
        "volume": 832.50871623
    },
    "1519660800": {
        "time": 1519660800,
        "low": 10168.0,
        "high": 10369.0,
        "open": 10220.99,
        "close": 10179.78,
        "volume": 1614.04225075
    },
    "1519664400": {
        "time": 1519664400,
        "low": 10108.36,
        "high": 10195.07,
        "open": 10179.77,
        "close": 10189.72,
        "volume": 1144.22719342
    },
    "1519668000": {
        "time": 1519668000,
        "low": 10178.11,
        "high": 10250.0,
        "open": 10189.71,
        "close": 10225.0,
        "volume": 700.70590523
    },
    "1519671600": {
        "time": 1519671600,
        "low": 10202.2,
        "high": 10279.8,
        "open": 10225.0,
        "close": 10220.02,
        "volume": 704.45751395
    },
    "1519675200": {
        "time": 1519675200,
        "low": 10167.56,
        "high": 10260.0,
        "open": 10220.15,
        "close": 10260.0,
        "volume": 715.1647942
    },
    "1519678800": {
        "time": 1519678800,
        "low": 10250.02,
        "high": 10447.74,
        "open": 10260.0,
        "close": 10375.17,
        "volume": 1877.1327085
    },
    "1519682400": {
        "time": 1519682400,
        "low": 10316.48,
        "high": 10399.0,
        "open": 10375.18,
        "close": 10351.0,
        "volume": 536.43533648
    },
    "1519686000": {
        "time": 1519686000,
        "low": 10250.0,
        "high": 10364.48,
        "open": 10351.01,
        "close": 10300.0,
        "volume": 677.30086047
    }
}