{
    "1455062400": {
        "time": 1455062400,
        "low": 372.01,
        "high": 373.3,
        "open": 372.76,
        "close": 372.01,
        "volume": 491.57876654
    },
    "1455066000": {
        "time": 1455066000,
        "low": 371.87,
        "high": 373.33,
        "open": 372.13,
        "close": 373.27,
        "volume": 338.31144438
    },
    "1455069600": {
        "time": 1455069600,
        "low": 372.39,
        "high": 373.29,
        "open": 373.27,
        "close": 372.64,
        "volume": 435.6484047
    },
    "1455073200": {
        "time": 1455073200,
        "low": 372.36,
        "high": 373.62,
        "open": 372.66,
        "close": 373.62,
        "volume": 296.43458259
    },
    "1455076800": {
        "time": 1455076800,
        "low": 373.46,
        "high": 374.95,
        "open": 373.63,
        "close": 374.19,
        "volume": 546.5917904
    },
    "1455080400": {
        "time": 1455080400,
        "low": 374.08,
        "high": 374.82,
        "open": 374.2,
        "close": 374.57,
        "volume": 286.21649767
    },
    "1455084000": {
        "time": 1455084000,
        "low": 373.87,
        "high": 374.69,
        "open": 374.57,
        "close": 374.55,
        "volume": 297.56353986
    },
    "1455087600": {
        "time": 1455087600,
        "low": 374.1,
        "high": 374.94,
        "open": 374.56,
        "close": 374.93,
        "volume": 238.59690555
    },
    "1455091200": {
        "time": 1455091200,
        "low": 374.11,
        "high": 375.0,
        "open": 374.92,
        "close": 374.95,
        "volume": 476.64660313
    },
    "1455094800": {
        "time": 1455094800,
        "low": 374.0,
        "high": 375.0,
        "open": 374.91,
        "close": 374.46,
        "volume": 306.19459722
    },
    "1455098400": {
        "time": 1455098400,
        "low": 373.75,
        "high": 374.92,
        "open": 374.54,
        "close": 374.56,
        "volume": 312.72416962
    },
    "1455102000": {
        "time": 1455102000,
        "low": 373.76,
        "high": 374.99,
        "open": 374.5,
        "close": 374.98,
        "volume": 402.05884302
    },
    "1455105600": {
        "time": 1455105600,
        "low": 374.93,
        "high": 377.2,
        "open": 374.99,
        "close": 377.01,
        "volume": 344.16367864
    },
    "1455109200": {
        "time": 1455109200,
        "low": 376.9,
        "high": 382.32,
        "open": 377.07,
        "close": 380.29,
        "volume": 510.50941255
    },
    "1455112800": {
        "time": 1455112800,
        "low": 380.09,
        "high": 383.34,
        "open": 380.35,
        "close": 382.0,
        "volume": 399.15629855
    },
    "1455116400": {
        "time": 1455116400,
        "low": 376.65,
        "high": 382.0,
        "open": 382.0,
        "close": 377.8,
        "volume": 629.15772946
    },
    "1455120000": {
        "time": 1455120000,
        "low": 377.64,
        "high": 380.4,
        "open": 377.94,
        "close": 377.82,
        "volume": 455.86040488
    },
    "1455123600": {
        "time": 1455123600,
        "low": 375.04,
        "high": 378.06,
        "open": 377.76,
        "close": 376.61,
        "volume": 344.93058279
    },
    "1455127200": {
        "time": 1455127200,
        "low": 375.77,
        "high": 378.6,
        "open": 376.61,
        "close": 378.0,
        "volume": 537.58058327
    },
    "1455130800": {
        "time": 1455130800,
        "low": 376.72,
        "high": 378.0,
        "open": 377.88,
        "close": 377.62,
        "volume": 457.30936549
    },
    "1455134400": {
        "time": 1455134400,
        "low": 376.77,
        "high": 378.48,
        "open": 377.68,
        "close": 378.12,
        "volume": 368.15749251
    },
    "1455138000": {
        "time": 1455138000,
        "low": 376.2,
        "high": 378.48,
        "open": 377.97,
        "close": 376.22,
        "volume": 452.88072916
    },
    "1455141600": {
        "time": 1455141600,
        "low": 376.28,
        "high": 378.31,
        "open": 377.09,
        "close": 377.33,
        "volume": 300.19220703
    },
    "1455145200": {
        "time": 1455145200,
        "low": 377.33,
        "high": 379.0,
        "open": 377.33,
        "close": 378.44,
        "volume": 507.57219574
    }
}