{
    "1538265600": {
        "time": 1538265600,
        "low": 6545.81,
        "high": 6581.0,
        "open": 6581.0,
        "close": 6559.0,
        "volume": 120.18896899
    },
    "1538269200": {
        "time": 1538269200,
        "low": 6558.99,
        "high": 6587.0,
        "open": 6559.0,
        "close": 6579.01,
        "volume": 101.13291802
    },
    "1538272800": {
        "time": 1538272800,
        "low": 6552.71,
        "high": 6581.0,
        "open": 6579.0,
        "close": 6557.74,
        "volume": 173.41653479
    },
    "1538276400": {
        "time": 1538276400,
        "low": 6556.97,
        "high": 6569.43,
        "open": 6559.48,
        "close": 6561.06,
        "volume": 99.4865496
    },
    "1538280000": {
        "time": 1538280000,
        "low": 6545.0,
        "high": 6563.01,
        "open": 6561.05,
        "close": 6546.95,
        "volume": 79.95417849
    },
    "1538283600": {
        "time": 1538283600,
        "low": 6543.21,
        "high": 6555.0,
        "open": 6546.95,
        "close": 6552.51,
        "volume": 91.45986348
    },
    "1538287200": {
        "time": 1538287200,
        "low": 6552.51,
        "high": 6568.91,
        "open": 6552.51,
        "close": 6568.9,
        "volume": 33.19611487
    },
    "1538290800": {
        "time": 1538290800,
        "low": 6552.65,
        "high": 6575.0,
        "open": 6568.9,
        "close": 6568.21,
        "volume": 117.68119075
    },
    "1538294400": {
        "time": 1538294400,
        "low": 6561.75,
        "high": 6569.84,
        "open": 6568.21,
        "close": 6566.12,
        "volume": 86.54564972
    },
    "1538298000": {
        "time": 1538298000,
        "low": 6560.53,
        "high": 6579.09,
        "open": 6566.13,
        "close": 6570.48,
        "volume": 92.88120063
    },
    "1538301600": {
        "time": 1538301600,
        "low": 6567.98,
        "high": 6632.28,
        "open": 6570.48,
        "close": 6624.25,
        "volume": 254.87453506
    },
    "1538305200": {
        "time": 1538305200,
        "low": 6603.88,
        "high": 6642.28,
        "open": 6624.25,
        "close": 6611.7,
        "volume": 170.89409634
    },
    "1538308800": {
        "time": 1538308800,
        "low": 6601.96,
        "high": 6616.91,
        "open": 6611.66,
        "close": 6613.97,
        "volume": 116.78784941
    },
    "1538312400": {
        "time": 1538312400,
        "low": 6608.22,
        "high": 6622.99,
        "open": 6613.96,
        "close": 6617.01,
        "volume": 143.91295615
    },
    "1538316000": {
        "time": 1538316000,
        "low": 6611.0,
        "high": 6640.26,
        "open": 6617.0,
        "close": 6627.51,
        "volume": 140.59546918
    },
    "1538319600": {
        "time": 1538319600,
        "low": 6580.0,
        "high": 6627.64,
        "open": 6627.64,
        "close": 6590.0,
        "volume": 268.29043069
    },
    "1538323200": {
        "time": 1538323200,
        "low": 6580.0,
        "high": 6609.4,
        "open": 6590.0,
        "close": 6604.01,
        "volume": 175.78953959
    },
    "1538326800": {
        "time": 1538326800,
        "low": 6589.98,
        "high": 6607.96,
        "open": 6604.0,
        "close": 6601.02,
        "volume": 151.45756679
    },
    "1538330400": {
        "time": 1538330400,
        "low": 6596.16,
        "high": 6609.91,
        "open": 6601.02,
        "close": 6598.24,
        "volume": 129.96075618
    },
    "1538334000": {
        "time": 1538334000,
        "low": 6581.71,
        "high": 6604.0,
        "open": 6598.25,
        "close": 6588.01,
        "volume": 145.5126098
    },
    "1538337600": {
        "time": 1538337600,
        "low": 6523.0,
        "high": 6588.01,
        "open": 6588.0,
        "close": 6561.3,
        "volume": 374.16191841
    },
    "1538341200": {
        "time": 1538341200,
        "low": 6545.3,
        "high": 6570.33,
        "open": 6561.31,
        "close": 6559.79,
        "volume": 160.72624547
    },
    "1538344800": {
        "time": 1538344800,
        "low": 6557.0,
        "high": 6616.83,
        "open": 6559.78,
        "close": 6612.05,
        "volume": 293.11258468
    },
    "1538348400": {
        "time": 1538348400,
        "low": 6594.81,
        "high": 6621.0,
        "open": 6612.05,
        "close": 6605.0,
        "volume": 176.70133995
    }
}