{
    "1549238400": {
        "time": 1549238400,
        "low": 3412.68,
        "high": 3427.21,
        "open": 3415.69,
        "close": 3420.01,
        "volume": 124.43708328
    },
    "1549242000": {
        "time": 1549242000,
        "low": 3416.37,
        "high": 3424.64,
        "open": 3420.01,
        "close": 3422.42,
        "volume": 175.05428941
    },
    "1549245600": {
        "time": 1549245600,
        "low": 3411.3,
        "high": 3423.26,
        "open": 3422.42,
        "close": 3412.09,
        "volume": 152.54279808
    },
    "1549249200": {
        "time": 1549249200,
        "low": 3411.62,
        "high": 3416.55,
        "open": 3412.09,
        "close": 3413.8,
        "volume": 123.39476437
    },
    "1549252800": {
        "time": 1549252800,
        "low": 3412.73,
        "high": 3420.0,
        "open": 3413.78,
        "close": 3416.02,
        "volume": 158.28550036
    },
    "1549256400": {
        "time": 1549256400,
        "low": 3413.0,
        "high": 3417.42,
        "open": 3416.01,
        "close": 3416.0,
        "volume": 145.86521561
    },
    "1549260000": {
        "time": 1549260000,
        "low": 3415.99,
        "high": 3421.0,
        "open": 3416.0,
        "close": 3417.79,
        "volume": 108.70169892
    },
    "1549263600": {
        "time": 1549263600,
        "low": 3416.0,
        "high": 3423.0,
        "open": 3417.78,
        "close": 3421.31,
        "volume": 71.1226079
    },
    "1549267200": {
        "time": 1549267200,
        "low": 3419.42,
        "high": 3435.0,
        "open": 3421.31,
        "close": 3420.72,
        "volume": 187.46588496
    },
    "1549270800": {
        "time": 1549270800,
        "low": 3404.3,
        "high": 3424.01,
        "open": 3420.72,
        "close": 3405.08,
        "volume": 247.10734118
    },
    "1549274400": {
        "time": 1549274400,
        "low": 3403.17,
        "high": 3411.69,
        "open": 3405.08,
        "close": 3408.24,
        "volume": 181.74392751
    },
    "1549278000": {
        "time": 1549278000,
        "low": 3398.29,
        "high": 3409.14,
        "open": 3408.24,
        "close": 3399.12,
        "volume": 232.72146513
    },
    "1549281600": {
        "time": 1549281600,
        "low": 3395.1,
        "high": 3407.73,
        "open": 3399.12,
        "close": 3405.02,
        "volume": 246.11132139
    },
    "1549285200": {
        "time": 1549285200,
        "low": 3403.4,
        "high": 3408.74,
        "open": 3405.01,
        "close": 3408.42,
        "volume": 194.77584767
    },
    "1549288800": {
        "time": 1549288800,
        "low": 3405.0,
        "high": 3413.3,
        "open": 3408.42,
        "close": 3405.8,
        "volume": 231.6891203
    },
    "1549292400": {
        "time": 1549292400,
        "low": 3405.01,
        "high": 3412.5,
        "open": 3405.81,
        "close": 3411.4,
        "volume": 356.1620787
    },
    "1549296000": {
        "time": 1549296000,
        "low": 3410.95,
        "high": 3416.59,
        "open": 3411.4,
        "close": 3411.34,
        "volume": 423.67176819
    },
    "1549299600": {
        "time": 1549299600,
        "low": 3410.5,
        "high": 3416.44,
        "open": 3411.34,
        "close": 3415.02,
        "volume": 340.02449007
    },
    "1549303200": {
        "time": 1549303200,
        "low": 3414.75,
        "high": 3422.0,
        "open": 3415.03,
        "close": 3418.26,
        "volume": 444.95461601
    },
    "1549306800": {
        "time": 1549306800,
        "low": 3414.01,
        "high": 3421.41,
        "open": 3418.26,
        "close": 3418.3,
        "volume": 487.07930194
    },
    "1549310400": {
        "time": 1549310400,
        "low": 3414.23,
        "high": 3422.0,
        "open": 3418.31,
        "close": 3414.51,
        "volume": 320.47639738
    },
    "1549314000": {
        "time": 1549314000,
        "low": 3414.5,
        "high": 3421.44,
        "open": 3414.51,
        "close": 3418.71,
        "volume": 346.09979962
    },
    "1549317600": {
        "time": 1549317600,
        "low": 3405.19,
        "high": 3418.31,
        "open": 3417.22,
        "close": 3408.61,
        "volume": 332.41397317
    },
    "1549321200": {
        "time": 1549321200,
        "low": 3406.54,
        "high": 3414.04,
        "open": 3408.61,
        "close": 3409.57,
        "volume": 400.91766169
    }
}