{
    "1526601600": {
        "time": 1526601600,
        "low": 7927.21,
        "high": 8059.0,
        "open": 8059.0,
        "close": 7954.91,
        "volume": 1014.44316753
    },
    "1526605200": {
        "time": 1526605200,
        "low": 7930.0,
        "high": 8010.99,
        "open": 7960.05,
        "close": 7979.99,
        "volume": 476.75572366
    },
    "1526608800": {
        "time": 1526608800,
        "low": 7952.46,
        "high": 8019.98,
        "open": 7980.0,
        "close": 7996.47,
        "volume": 304.84360704
    },
    "1526612400": {
        "time": 1526612400,
        "low": 7987.68,
        "high": 8026.0,
        "open": 7996.63,
        "close": 7996.88,
        "volume": 215.03623667
    },
    "1526616000": {
        "time": 1526616000,
        "low": 7998.93,
        "high": 8067.16,
        "open": 7998.93,
        "close": 8022.6,
        "volume": 411.99381905
    },
    "1526619600": {
        "time": 1526619600,
        "low": 7990.1,
        "high": 8054.59,
        "open": 8022.6,
        "close": 8040.29,
        "volume": 229.43430229
    },
    "1526623200": {
        "time": 1526623200,
        "low": 7951.54,
        "high": 8040.3,
        "open": 8040.3,
        "close": 7972.6,
        "volume": 352.50238237
    },
    "1526626800": {
        "time": 1526626800,
        "low": 7972.6,
        "high": 8172.82,
        "open": 7972.6,
        "close": 8094.99,
        "volume": 775.65786945
    },
    "1526630400": {
        "time": 1526630400,
        "low": 8082.16,
        "high": 8139.96,
        "open": 8095.0,
        "close": 8125.0,
        "volume": 164.67212024
    },
    "1526634000": {
        "time": 1526634000,
        "low": 8084.45,
        "high": 8136.5,
        "open": 8125.0,
        "close": 8110.0,
        "volume": 113.2727949
    },
    "1526637600": {
        "time": 1526637600,
        "low": 8091.76,
        "high": 8148.38,
        "open": 8109.31,
        "close": 8130.59,
        "volume": 92.64161363
    },
    "1526641200": {
        "time": 1526641200,
        "low": 8051.0,
        "high": 8133.89,
        "open": 8130.58,
        "close": 8109.0,
        "volume": 332.68148618
    },
    "1526644800": {
        "time": 1526644800,
        "low": 8085.17,
        "high": 8139.99,
        "open": 8110.0,
        "close": 8110.51,
        "volume": 165.01783754
    },
    "1526648400": {
        "time": 1526648400,
        "low": 8067.11,
        "high": 8124.6,
        "open": 8111.66,
        "close": 8103.32,
        "volume": 204.02308871
    },
    "1526652000": {
        "time": 1526652000,
        "low": 8047.08,
        "high": 8098.3,
        "open": 8098.3,
        "close": 8082.08,
        "volume": 274.62093463
    },
    "1526655600": {
        "time": 1526655600,
        "low": 8070.32,
        "high": 8132.84,
        "open": 8082.07,
        "close": 8113.13,
        "volume": 279.94431759
    },
    "1526659200": {
        "time": 1526659200,
        "low": 8089.21,
        "high": 8145.0,
        "open": 8113.13,
        "close": 8130.1,
        "volume": 375.19793522
    },
    "1526662800": {
        "time": 1526662800,
        "low": 8100.0,
        "high": 8140.0,
        "open": 8126.44,
        "close": 8113.56,
        "volume": 186.82174939
    },
    "1526666400": {
        "time": 1526666400,
        "low": 8088.01,
        "high": 8230.0,
        "open": 8113.55,
        "close": 8216.0,
        "volume": 807.62102195
    },
    "1526670000": {
        "time": 1526670000,
        "low": 8185.17,
        "high": 8280.0,
        "open": 8216.01,
        "close": 8227.35,
        "volume": 788.95243479
    },
    "1526673600": {
        "time": 1526673600,
        "low": 8210.91,
        "high": 8247.1,
        "open": 8227.35,
        "close": 8220.0,
        "volume": 234.81429301
    },
    "1526677200": {
        "time": 1526677200,
        "low": 8220.01,
        "high": 8263.96,
        "open": 8220.01,
        "close": 8231.77,
        "volume": 182.42940731
    },
    "1526680800": {
        "time": 1526680800,
        "low": 8212.6,
        "high": 8249.0,
        "open": 8231.77,
        "close": 8219.99,
        "volume": 115.28356083
    },
    "1526684400": {
        "time": 1526684400,
        "low": 8219.99,
        "high": 8247.74,
        "open": 8219.99,
        "close": 8238.51,
        "volume": 140.61422233
    }
}