{
    "1479600000": {
        "time": 1479600000,
        "low": 750.74,
        "high": 752.47,
        "open": 750.77,
        "close": 752.47,
        "volume": 84.05284464
    },
    "1479603600": {
        "time": 1479603600,
        "low": 751.77,
        "high": 753.81,
        "open": 752.47,
        "close": 752.37,
        "volume": 134.88410602
    },
    "1479607200": {
        "time": 1479607200,
        "low": 750.22,
        "high": 753.0,
        "open": 752.41,
        "close": 753.0,
        "volume": 178.12520062
    },
    "1479610800": {
        "time": 1479610800,
        "low": 750.74,
        "high": 753.0,
        "open": 753.0,
        "close": 751.12,
        "volume": 99.2687105
    },
    "1479614400": {
        "time": 1479614400,
        "low": 750.22,
        "high": 752.41,
        "open": 751.12,
        "close": 751.53,
        "volume": 94.12734184
    },
    "1479618000": {
        "time": 1479618000,
        "low": 749.75,
        "high": 752.99,
        "open": 751.53,
        "close": 750.93,
        "volume": 96.95157
    },
    "1479621600": {
        "time": 1479621600,
        "low": 748.85,
        "high": 751.16,
        "open": 750.79,
        "close": 749.79,
        "volume": 78.9820697
    },
    "1479625200": {
        "time": 1479625200,
        "low": 748.21,
        "high": 751.67,
        "open": 749.68,
        "close": 751.21,
        "volume": 50.7623175
    },
    "1479628800": {
        "time": 1479628800,
        "low": 749.02,
        "high": 751.12,
        "open": 750.77,
        "close": 750.69,
        "volume": 27.65897667
    },
    "1479632400": {
        "time": 1479632400,
        "low": 748.92,
        "high": 751.0,
        "open": 750.69,
        "close": 750.41,
        "volume": 38.14924494
    },
    "1479636000": {
        "time": 1479636000,
        "low": 748.4,
        "high": 751.11,
        "open": 750.4,
        "close": 749.49,
        "volume": 47.22609196
    },
    "1479639600": {
        "time": 1479639600,
        "low": 748.4,
        "high": 749.82,
        "open": 749.49,
        "close": 748.97,
        "volume": 30.94215205
    },
    "1479643200": {
        "time": 1479643200,
        "low": 747.95,
        "high": 749.83,
        "open": 748.97,
        "close": 749.52,
        "volume": 49.3897333
    },
    "1479646800": {
        "time": 1479646800,
        "low": 733.65,
        "high": 749.31,
        "open": 749.31,
        "close": 738.07,
        "volume": 336.18401331
    },
    "1479650400": {
        "time": 1479650400,
        "low": 732.94,
        "high": 740.46,
        "open": 738.24,
        "close": 732.94,
        "volume": 246.87018361
    },
    "1479654000": {
        "time": 1479654000,
        "low": 727.34,
        "high": 736.26,
        "open": 732.93,
        "close": 729.88,
        "volume": 711.10827467
    },
    "1479657600": {
        "time": 1479657600,
        "low": 726.61,
        "high": 733.83,
        "open": 729.98,
        "close": 733.46,
        "volume": 261.06446093
    },
    "1479661200": {
        "time": 1479661200,
        "low": 725.0,
        "high": 733.14,
        "open": 733.08,
        "close": 729.16,
        "volume": 199.62876381
    },
    "1479664800": {
        "time": 1479664800,
        "low": 715.0,
        "high": 730.25,
        "open": 729.65,
        "close": 718.04,
        "volume": 668.47745247
    },
    "1479668400": {
        "time": 1479668400,
        "low": 715.26,
        "high": 730.5,
        "open": 717.86,
        "close": 728.99,
        "volume": 317.06442144
    },
    "1479672000": {
        "time": 1479672000,
        "low": 727.55,
        "high": 729.34,
        "open": 728.99,
        "close": 727.98,
        "volume": 132.55144105
    },
    "1479675600": {
        "time": 1479675600,
        "low": 725.6,
        "high": 728.0,
        "open": 727.98,
        "close": 727.42,
        "volume": 148.34404599
    },
    "1479679200": {
        "time": 1479679200,
        "low": 727.43,
        "high": 730.99,
        "open": 727.43,
        "close": 730.82,
        "volume": 151.23774487
    },
    "1479682800": {
        "time": 1479682800,
        "low": 730.33,
        "high": 731.99,
        "open": 730.44,
        "close": 731.99,
        "volume": 139.07387414
    }
}