{
    "1460505600": {
        "time": 1460505600,
        "low": 426.77,
        "high": 428.31,
        "open": 427.8,
        "close": 427.92,
        "volume": 328.34437249
    },
    "1460509200": {
        "time": 1460509200,
        "low": 427.74,
        "high": 428.5,
        "open": 427.86,
        "close": 428.5,
        "volume": 234.27664187
    },
    "1460512800": {
        "time": 1460512800,
        "low": 428.34,
        "high": 429.44,
        "open": 428.46,
        "close": 429.2,
        "volume": 241.4114842
    },
    "1460516400": {
        "time": 1460516400,
        "low": 428.49,
        "high": 429.24,
        "open": 429.21,
        "close": 428.97,
        "volume": 295.86940159
    },
    "1460520000": {
        "time": 1460520000,
        "low": 428.14,
        "high": 429.13,
        "open": 428.96,
        "close": 428.39,
        "volume": 160.59405632
    },
    "1460523600": {
        "time": 1460523600,
        "low": 427.68,
        "high": 428.45,
        "open": 428.4,
        "close": 427.68,
        "volume": 111.38177107
    },
    "1460527200": {
        "time": 1460527200,
        "low": 427.48,
        "high": 429.4,
        "open": 427.78,
        "close": 428.95,
        "volume": 468.2395079
    },
    "1460530800": {
        "time": 1460530800,
        "low": 427.53,
        "high": 428.97,
        "open": 428.87,
        "close": 427.97,
        "volume": 85.79820227
    },
    "1460534400": {
        "time": 1460534400,
        "low": 426.07,
        "high": 427.93,
        "open": 427.93,
        "close": 426.08,
        "volume": 160.27305017
    },
    "1460538000": {
        "time": 1460538000,
        "low": 425.54,
        "high": 426.08,
        "open": 426.07,
        "close": 425.66,
        "volume": 96.72882495
    },
    "1460541600": {
        "time": 1460541600,
        "low": 425.25,
        "high": 425.95,
        "open": 425.66,
        "close": 425.83,
        "volume": 141.7159752
    },
    "1460545200": {
        "time": 1460545200,
        "low": 425.0,
        "high": 425.88,
        "open": 425.84,
        "close": 425.88,
        "volume": 152.25874691
    },
    "1460548800": {
        "time": 1460548800,
        "low": 424.18,
        "high": 426.3,
        "open": 425.88,
        "close": 424.41,
        "volume": 299.33016628
    },
    "1460552400": {
        "time": 1460552400,
        "low": 423.59,
        "high": 424.72,
        "open": 424.41,
        "close": 424.72,
        "volume": 307.56471391
    },
    "1460556000": {
        "time": 1460556000,
        "low": 424.56,
        "high": 426.09,
        "open": 424.73,
        "close": 425.9,
        "volume": 264.72926646
    },
    "1460559600": {
        "time": 1460559600,
        "low": 425.62,
        "high": 426.19,
        "open": 425.89,
        "close": 425.95,
        "volume": 192.18810365
    },
    "1460563200": {
        "time": 1460563200,
        "low": 425.67,
        "high": 426.2,
        "open": 425.94,
        "close": 426.0,
        "volume": 247.75726826
    },
    "1460566800": {
        "time": 1460566800,
        "low": 425.76,
        "high": 426.91,
        "open": 426.09,
        "close": 426.54,
        "volume": 394.10352061
    },
    "1460570400": {
        "time": 1460570400,
        "low": 425.81,
        "high": 427.1,
        "open": 426.5,
        "close": 426.11,
        "volume": 225.52424662
    },
    "1460574000": {
        "time": 1460574000,
        "low": 424.41,
        "high": 426.5,
        "open": 426.02,
        "close": 424.73,
        "volume": 591.95449961
    },
    "1460577600": {
        "time": 1460577600,
        "low": 424.19,
        "high": 425.59,
        "open": 424.74,
        "close": 425.59,
        "volume": 254.20372166
    },
    "1460581200": {
        "time": 1460581200,
        "low": 425.1,
        "high": 425.93,
        "open": 425.59,
        "close": 425.73,
        "volume": 240.60882415
    },
    "1460584800": {
        "time": 1460584800,
        "low": 425.16,
        "high": 426.0,
        "open": 425.74,
        "close": 425.8,
        "volume": 192.53984943
    },
    "1460588400": {
        "time": 1460588400,
        "low": 425.3,
        "high": 425.87,
        "open": 425.82,
        "close": 425.58,
        "volume": 197.67892918
    }
}