{
    "1559779200": {
        "time": 1559779200,
        "low": 7750.68,
        "high": 7829.78,
        "open": 7787.36,
        "close": 7800.12,
        "volume": 377.62703108
    },
    "1559782800": {
        "time": 1559782800,
        "low": 7784.81,
        "high": 7874.68,
        "open": 7800.09,
        "close": 7840.54,
        "volume": 356.71018397
    },
    "1559786400": {
        "time": 1559786400,
        "low": 7802.85,
        "high": 7861.0,
        "open": 7840.38,
        "close": 7821.69,
        "volume": 373.63273721
    },
    "1559790000": {
        "time": 1559790000,
        "low": 7817.13,
        "high": 7870.0,
        "open": 7821.68,
        "close": 7865.81,
        "volume": 220.17986905
    },
    "1559793600": {
        "time": 1559793600,
        "low": 7811.01,
        "high": 7865.32,
        "open": 7865.32,
        "close": 7832.6,
        "volume": 186.32347067
    },
    "1559797200": {
        "time": 1559797200,
        "low": 7770.0,
        "high": 7841.0,
        "open": 7832.59,
        "close": 7795.0,
        "volume": 316.22090526
    },
    "1559800800": {
        "time": 1559800800,
        "low": 7786.32,
        "high": 7820.37,
        "open": 7794.99,
        "close": 7814.0,
        "volume": 134.77191885
    },
    "1559804400": {
        "time": 1559804400,
        "low": 7760.0,
        "high": 7827.0,
        "open": 7814.0,
        "close": 7768.17,
        "volume": 135.26680404
    },
    "1559808000": {
        "time": 1559808000,
        "low": 7740.5,
        "high": 7810.0,
        "open": 7768.17,
        "close": 7810.0,
        "volume": 149.09494144
    },
    "1559811600": {
        "time": 1559811600,
        "low": 7770.6,
        "high": 7820.0,
        "open": 7809.99,
        "close": 7774.79,
        "volume": 156.50994302
    },
    "1559815200": {
        "time": 1559815200,
        "low": 7766.65,
        "high": 7815.0,
        "open": 7775.11,
        "close": 7810.48,
        "volume": 117.60329915
    },
    "1559818800": {
        "time": 1559818800,
        "low": 7802.86,
        "high": 7856.78,
        "open": 7809.03,
        "close": 7850.3,
        "volume": 218.0495811
    },
    "1559822400": {
        "time": 1559822400,
        "low": 7720.18,
        "high": 7865.0,
        "open": 7850.3,
        "close": 7772.01,
        "volume": 903.70094986
    },
    "1559826000": {
        "time": 1559826000,
        "low": 7654.64,
        "high": 7771.78,
        "open": 7771.78,
        "close": 7742.18,
        "volume": 950.10546428
    },
    "1559829600": {
        "time": 1559829600,
        "low": 7592.93,
        "high": 7742.9,
        "open": 7741.97,
        "close": 7696.77,
        "volume": 1216.55975231
    },
    "1559833200": {
        "time": 1559833200,
        "low": 7670.0,
        "high": 7726.17,
        "open": 7696.77,
        "close": 7710.73,
        "volume": 479.17060828
    },
    "1559836800": {
        "time": 1559836800,
        "low": 7689.96,
        "high": 7735.24,
        "open": 7710.72,
        "close": 7715.68,
        "volume": 434.90193698
    },
    "1559840400": {
        "time": 1559840400,
        "low": 7637.37,
        "high": 7717.98,
        "open": 7715.68,
        "close": 7649.56,
        "volume": 393.28284708
    },
    "1559844000": {
        "time": 1559844000,
        "low": 7450.0,
        "high": 7660.93,
        "open": 7645.53,
        "close": 7594.83,
        "volume": 2686.799242
    },
    "1559847600": {
        "time": 1559847600,
        "low": 7558.73,
        "high": 7620.0,
        "open": 7594.8,
        "close": 7599.22,
        "volume": 498.97315095
    },
    "1559851200": {
        "time": 1559851200,
        "low": 7577.8,
        "high": 7716.99,
        "open": 7599.01,
        "close": 7685.08,
        "volume": 553.90355097
    },
    "1559854800": {
        "time": 1559854800,
        "low": 7682.66,
        "high": 7748.03,
        "open": 7685.08,
        "close": 7738.94,
        "volume": 359.13970438
    },
    "1559858400": {
        "time": 1559858400,
        "low": 7704.32,
        "high": 7747.28,
        "open": 7738.94,
        "close": 7733.37,
        "volume": 298.89883734
    },
    "1559862000": {
        "time": 1559862000,
        "low": 7721.23,
        "high": 7828.02,
        "open": 7733.38,
        "close": 7805.0,
        "volume": 1008.65242553
    }
}