{
    "1543536000": {
        "time": 1543536000,
        "low": 4180.2,
        "high": 4258.01,
        "open": 4247.99,
        "close": 4197.17,
        "volume": 559.96065525
    },
    "1543539600": {
        "time": 1543539600,
        "low": 4171.84,
        "high": 4219.59,
        "open": 4197.16,
        "close": 4207.52,
        "volume": 524.58276516
    },
    "1543543200": {
        "time": 1543543200,
        "low": 4197.93,
        "high": 4280.0,
        "open": 4207.51,
        "close": 4268.66,
        "volume": 1071.11224902
    },
    "1543546800": {
        "time": 1543546800,
        "low": 4245.0,
        "high": 4290.0,
        "open": 4267.52,
        "close": 4253.31,
        "volume": 606.94799372
    },
    "1543550400": {
        "time": 1543550400,
        "low": 4231.01,
        "high": 4288.0,
        "open": 4253.29,
        "close": 4274.0,
        "volume": 478.49868641
    },
    "1543554000": {
        "time": 1543554000,
        "low": 4257.01,
        "high": 4297.71,
        "open": 4270.01,
        "close": 4264.65,
        "volume": 527.75237558
    },
    "1543557600": {
        "time": 1543557600,
        "low": 4233.73,
        "high": 4279.33,
        "open": 4264.64,
        "close": 4233.73,
        "volume": 425.64109196
    },
    "1543561200": {
        "time": 1543561200,
        "low": 4140.0,
        "high": 4237.57,
        "open": 4233.35,
        "close": 4162.13,
        "volume": 1063.10224209
    },
    "1543564800": {
        "time": 1543564800,
        "low": 4136.04,
        "high": 4196.78,
        "open": 4162.0,
        "close": 4166.78,
        "volume": 349.42022741
    },
    "1543568400": {
        "time": 1543568400,
        "low": 4145.58,
        "high": 4186.15,
        "open": 4166.78,
        "close": 4163.16,
        "volume": 217.4851875
    },
    "1543572000": {
        "time": 1543572000,
        "low": 4014.0,
        "high": 4165.43,
        "open": 4165.42,
        "close": 4015.0,
        "volume": 1596.28083119
    },
    "1543575600": {
        "time": 1543575600,
        "low": 3928.59,
        "high": 4015.01,
        "open": 4015.0,
        "close": 3945.01,
        "volume": 2135.85323892
    },
    "1543579200": {
        "time": 1543579200,
        "low": 3869.0,
        "high": 3990.04,
        "open": 3945.01,
        "close": 3970.11,
        "volume": 2553.5165438
    },
    "1543582800": {
        "time": 1543582800,
        "low": 3950.0,
        "high": 4020.0,
        "open": 3970.11,
        "close": 3984.0,
        "volume": 982.10172745
    },
    "1543586400": {
        "time": 1543586400,
        "low": 3932.73,
        "high": 3988.02,
        "open": 3984.18,
        "close": 3976.42,
        "volume": 707.08487364
    },
    "1543590000": {
        "time": 1543590000,
        "low": 3905.0,
        "high": 3976.42,
        "open": 3976.41,
        "close": 3968.4,
        "volume": 1117.79331482
    },
    "1543593600": {
        "time": 1543593600,
        "low": 3952.0,
        "high": 4016.18,
        "open": 3968.4,
        "close": 4013.36,
        "volume": 752.41171307
    },
    "1543597200": {
        "time": 1543597200,
        "low": 3985.0,
        "high": 4020.0,
        "open": 4013.36,
        "close": 3993.08,
        "volume": 585.4221102
    },
    "1543600800": {
        "time": 1543600800,
        "low": 3964.68,
        "high": 4003.42,
        "open": 3995.0,
        "close": 3972.39,
        "volume": 478.84686894
    },
    "1543604400": {
        "time": 1543604400,
        "low": 3965.4,
        "high": 3997.0,
        "open": 3972.39,
        "close": 3967.84,
        "volume": 478.19886329
    },
    "1543608000": {
        "time": 1543608000,
        "low": 3936.36,
        "high": 3982.0,
        "open": 3967.84,
        "close": 3957.92,
        "volume": 523.83376839
    },
    "1543611600": {
        "time": 1543611600,
        "low": 3870.0,
        "high": 3979.0,
        "open": 3957.83,
        "close": 3935.0,
        "volume": 1132.10717627
    },
    "1543615200": {
        "time": 1543615200,
        "low": 3900.0,
        "high": 3953.84,
        "open": 3932.38,
        "close": 3943.93,
        "volume": 598.86216815
    },
    "1543618800": {
        "time": 1543618800,
        "low": 3940.0,
        "high": 3990.0,
        "open": 3946.32,
        "close": 3976.0,
        "volume": 543.57020952
    }
}