{
    "1523404800": {
        "time": 1523404800,
        "low": 6824.99,
        "high": 6849.0,
        "open": 6825.0,
        "close": 6837.5,
        "volume": 345.99918875
    },
    "1523408400": {
        "time": 1523408400,
        "low": 6824.99,
        "high": 6846.0,
        "open": 6837.5,
        "close": 6836.0,
        "volume": 220.3923215
    },
    "1523412000": {
        "time": 1523412000,
        "low": 6831.7,
        "high": 6848.5,
        "open": 6835.99,
        "close": 6840.0,
        "volume": 257.32490539
    },
    "1523415600": {
        "time": 1523415600,
        "low": 6806.01,
        "high": 6841.99,
        "open": 6840.0,
        "close": 6818.0,
        "volume": 294.6204596
    },
    "1523419200": {
        "time": 1523419200,
        "low": 6817.99,
        "high": 6827.99,
        "open": 6818.0,
        "close": 6827.98,
        "volume": 87.01235671
    },
    "1523422800": {
        "time": 1523422800,
        "low": 6826.72,
        "high": 6859.0,
        "open": 6827.98,
        "close": 6826.72,
        "volume": 420.14218475
    },
    "1523426400": {
        "time": 1523426400,
        "low": 6810.0,
        "high": 6840.0,
        "open": 6826.73,
        "close": 6839.99,
        "volume": 211.60804791
    },
    "1523430000": {
        "time": 1523430000,
        "low": 6839.99,
        "high": 6844.38,
        "open": 6840.0,
        "close": 6844.38,
        "volume": 84.13930835
    },
    "1523433600": {
        "time": 1523433600,
        "low": 6844.37,
        "high": 6858.75,
        "open": 6844.38,
        "close": 6854.0,
        "volume": 105.25533592
    },
    "1523437200": {
        "time": 1523437200,
        "low": 6849.8,
        "high": 6857.5,
        "open": 6853.99,
        "close": 6853.32,
        "volume": 83.58816394
    },
    "1523440800": {
        "time": 1523440800,
        "low": 6839.9,
        "high": 6853.33,
        "open": 6853.33,
        "close": 6841.23,
        "volume": 146.30596406
    },
    "1523444400": {
        "time": 1523444400,
        "low": 6819.0,
        "high": 6858.0,
        "open": 6841.23,
        "close": 6857.82,
        "volume": 206.91679149
    },
    "1523448000": {
        "time": 1523448000,
        "low": 6845.0,
        "high": 6857.81,
        "open": 6857.81,
        "close": 6854.91,
        "volume": 160.90624985
    },
    "1523451600": {
        "time": 1523451600,
        "low": 6854.9,
        "high": 6960.0,
        "open": 6854.9,
        "close": 6932.0,
        "volume": 1273.38258542
    },
    "1523455200": {
        "time": 1523455200,
        "low": 6932.0,
        "high": 6954.0,
        "open": 6932.0,
        "close": 6938.01,
        "volume": 367.03688289
    },
    "1523458800": {
        "time": 1523458800,
        "low": 6917.0,
        "high": 6938.01,
        "open": 6938.01,
        "close": 6929.99,
        "volume": 355.34992331
    },
    "1523462400": {
        "time": 1523462400,
        "low": 6906.0,
        "high": 6930.0,
        "open": 6930.0,
        "close": 6917.98,
        "volume": 452.97711852
    },
    "1523466000": {
        "time": 1523466000,
        "low": 6870.7,
        "high": 6918.0,
        "open": 6917.98,
        "close": 6902.0,
        "volume": 471.65054464
    },
    "1523469600": {
        "time": 1523469600,
        "low": 6892.38,
        "high": 6909.97,
        "open": 6902.0,
        "close": 6901.48,
        "volume": 382.0628392
    },
    "1523473200": {
        "time": 1523473200,
        "low": 6896.97,
        "high": 6914.93,
        "open": 6901.48,
        "close": 6914.47,
        "volume": 341.04616521
    },
    "1523476800": {
        "time": 1523476800,
        "low": 6884.43,
        "high": 6914.48,
        "open": 6914.48,
        "close": 6889.92,
        "volume": 409.73891188
    },
    "1523480400": {
        "time": 1523480400,
        "low": 6882.2,
        "high": 6898.95,
        "open": 6889.92,
        "close": 6898.95,
        "volume": 189.85664655
    },
    "1523484000": {
        "time": 1523484000,
        "low": 6898.94,
        "high": 6915.0,
        "open": 6898.94,
        "close": 6915.0,
        "volume": 284.08665571
    },
    "1523487600": {
        "time": 1523487600,
        "low": 6914.99,
        "high": 6974.0,
        "open": 6915.0,
        "close": 6942.99,
        "volume": 1031.59645455
    }
}