{
    "1462320000": {
        "time": 1462320000,
        "low": 452.1,
        "high": 453.23,
        "open": 452.21,
        "close": 452.58,
        "volume": 226.66421291
    },
    "1462323600": {
        "time": 1462323600,
        "low": 452.02,
        "high": 452.6,
        "open": 452.58,
        "close": 452.2,
        "volume": 215.30997263
    },
    "1462327200": {
        "time": 1462327200,
        "low": 452.02,
        "high": 452.48,
        "open": 452.23,
        "close": 452.46,
        "volume": 199.6966693
    },
    "1462330800": {
        "time": 1462330800,
        "low": 450.32,
        "high": 452.39,
        "open": 452.39,
        "close": 450.59,
        "volume": 264.82939167
    },
    "1462334400": {
        "time": 1462334400,
        "low": 450.06,
        "high": 451.39,
        "open": 450.42,
        "close": 451.0,
        "volume": 180.72103277
    },
    "1462338000": {
        "time": 1462338000,
        "low": 450.9,
        "high": 452.15,
        "open": 451.0,
        "close": 452.15,
        "volume": 90.86286867
    },
    "1462341600": {
        "time": 1462341600,
        "low": 451.21,
        "high": 452.17,
        "open": 452.1,
        "close": 452.06,
        "volume": 98.64195871
    },
    "1462345200": {
        "time": 1462345200,
        "low": 451.63,
        "high": 452.21,
        "open": 452.07,
        "close": 452.2,
        "volume": 95.50807848
    },
    "1462348800": {
        "time": 1462348800,
        "low": 450.79,
        "high": 452.15,
        "open": 452.11,
        "close": 451.14,
        "volume": 72.17446111
    },
    "1462352400": {
        "time": 1462352400,
        "low": 448.55,
        "high": 451.34,
        "open": 451.0,
        "close": 448.55,
        "volume": 97.24908176
    },
    "1462356000": {
        "time": 1462356000,
        "low": 448.0,
        "high": 449.46,
        "open": 448.55,
        "close": 448.01,
        "volume": 175.22787466
    },
    "1462359600": {
        "time": 1462359600,
        "low": 447.0,
        "high": 448.17,
        "open": 448.15,
        "close": 447.33,
        "volume": 235.36486175
    },
    "1462363200": {
        "time": 1462363200,
        "low": 446.76,
        "high": 447.52,
        "open": 447.28,
        "close": 447.02,
        "volume": 200.57255351
    },
    "1462366800": {
        "time": 1462366800,
        "low": 447.01,
        "high": 448.74,
        "open": 447.02,
        "close": 448.32,
        "volume": 188.66250808
    },
    "1462370400": {
        "time": 1462370400,
        "low": 448.04,
        "high": 449.67,
        "open": 448.37,
        "close": 449.11,
        "volume": 211.43644228
    },
    "1462374000": {
        "time": 1462374000,
        "low": 448.11,
        "high": 449.1,
        "open": 449.1,
        "close": 448.71,
        "volume": 188.62087941
    },
    "1462377600": {
        "time": 1462377600,
        "low": 448.13,
        "high": 449.01,
        "open": 448.71,
        "close": 448.36,
        "volume": 289.84753804
    },
    "1462381200": {
        "time": 1462381200,
        "low": 447.73,
        "high": 449.0,
        "open": 448.4,
        "close": 448.08,
        "volume": 337.84092564
    },
    "1462384800": {
        "time": 1462384800,
        "low": 447.79,
        "high": 448.67,
        "open": 448.08,
        "close": 448.05,
        "volume": 192.18328896
    },
    "1462388400": {
        "time": 1462388400,
        "low": 447.59,
        "high": 448.59,
        "open": 448.05,
        "close": 447.74,
        "volume": 283.01705732
    },
    "1462392000": {
        "time": 1462392000,
        "low": 447.0,
        "high": 448.06,
        "open": 447.82,
        "close": 447.47,
        "volume": 264.67447028
    },
    "1462395600": {
        "time": 1462395600,
        "low": 447.29,
        "high": 448.55,
        "open": 447.33,
        "close": 448.21,
        "volume": 197.94695788
    },
    "1462399200": {
        "time": 1462399200,
        "low": 448.21,
        "high": 449.28,
        "open": 448.21,
        "close": 448.6,
        "volume": 258.84157235
    },
    "1462402800": {
        "time": 1462402800,
        "low": 447.39,
        "high": 449.28,
        "open": 448.67,
        "close": 448.68,
        "volume": 317.64535659
    }
}